{
  "id": "27-passport-local",
  "trail": "advanced",
  "order": 27,
  "title": {
    "pt": "Autenticação com Passport.js (LocalStrategy)",
    "en": "Authentication with Passport.js (LocalStrategy)",
    "es": "Autenticación con Passport.js (LocalStrategy)",
    "de": "Authentifizierung mit Passport.js (LocalStrategy)",
    "it": "Autenticazione con Passport.js (LocalStrategy)",
    "fr": "Authentification avec Passport.js (LocalStrategy)"
  },
  "theory": {
    "pt": "Passport.js é o middleware de autenticação mais usado no ecossistema Express. Em vez de implementar do zero a lógica de login para cada método de autenticação (usuário/senha, Google, GitHub, JWT...), o Passport organiza isso em **estrategias** (`Strategy`) — módulos plugáveis, cada um implementando um mecanismo específico de autenticação.\n\nA `LocalStrategy` (do pacote `passport-local`) implementa o caso mais simples: autenticação por usuário e senha, validados localmente pela sua própria aplicação (em vez de um provedor externo como o Google). Você a configura informando uma função de verificação:\n\n  const LocalStrategy = require('passport-local').Strategy;\n\n  passport.use(new LocalStrategy((username, password, done) => {\n    if (username === 'admin' && password === '1234') {\n      return done(null, { username });\n    }\n    return done(null, false);\n  }));\n\nA função de verificação chama `done(erro, usuario)`: passe `null, dadosDoUsuario` em caso de sucesso, ou `null, false` se as credenciais forem inválidas (reservando o primeiro argumento para erros inesperados, como falha de conexão com o banco).\n\nPara usar a estratégia em uma rota, você invoca `passport.authenticate('local', opcoes)` como middleware:\n\n  app.post('/login', passport.authenticate('local', { session: false }), (req, res) => {\n    res.json({ ok: true, user: req.user });\n  });\n\nQuando a autenticação tem sucesso, o Passport popula `req.user` com o objeto retornado por `done()`, e a requisição segue para o próximo handler. Quando falha, o Passport responde automaticamente com `401 Unauthorized`.\n\nEm aplicações que usam sessões (em vez de JWT), o Passport também define `serializeUser` (para decidir o que salvar na sessão depois do login — geralmente apenas o ID do usuário) e `deserializeUser` (para reconstruir o usuário completo a partir desse ID em cada requisição subsequente). A opção `{ session: false }`, usada aqui, desativa essa integração, já que esse exercício foca apenas na estratégia local em si.",
    "en": "Passport.js is the most widely used authentication middleware in the Express ecosystem. Instead of implementing login logic from scratch for every authentication method (username/password, Google, GitHub, JWT...), Passport organizes this into **strategies** (`Strategy`) — pluggable modules, each implementing a specific authentication mechanism.\n\nThe `LocalStrategy` (from the `passport-local` package) implements the simplest case: username and password authentication, validated locally by your own application (instead of an external provider like Google). You configure it by providing a verify function:\n\n  const LocalStrategy = require('passport-local').Strategy;\n\n  passport.use(new LocalStrategy((username, password, done) => {\n    if (username === 'admin' && password === '1234') {\n      return done(null, { username });\n    }\n    return done(null, false);\n  }));\n\nThe verify function calls `done(error, user)`: pass `null, userData` on success, or `null, false` if the credentials are invalid (reserving the first argument for unexpected errors, like a database connection failure).\n\nTo use the strategy on a route, you invoke `passport.authenticate('local', options)` as middleware:\n\n  app.post('/login', passport.authenticate('local', { session: false }), (req, res) => {\n    res.json({ ok: true, user: req.user });\n  });\n\nWhen authentication succeeds, Passport populates `req.user` with the object returned by `done()`, and the request moves on to the next handler. When it fails, Passport automatically responds with `401 Unauthorized`.\n\nIn applications that use sessions (instead of JWT), Passport also defines `serializeUser` (to decide what to save in the session after login — usually just the user's ID) and `deserializeUser` (to reconstruct the full user from that ID on every subsequent request). The `{ session: false }` option, used here, disables that integration, since this exercise focuses purely on the local strategy itself.",
    "es": "Passport.js es el middleware de autenticación más usado en el ecosistema Express. En lugar de implementar desde cero la lógica de inicio de sesión para cada método de autenticación (usuario/contraseña, Google, GitHub, JWT...), Passport organiza esto en **estrategias** (`Strategy`) — módulos conectables, cada uno implementando un mecanismo específico de autenticación.\n\nLa `LocalStrategy` (del paquete `passport-local`) implementa el caso más simple: autenticación por usuario y contraseña, validados localmente por tu propia aplicación (en lugar de un proveedor externo como Google). La configuras proporcionando una función de verificación:\n\n  const LocalStrategy = require('passport-local').Strategy;\n\n  passport.use(new LocalStrategy((username, password, done) => {\n    if (username === 'admin' && password === '1234') {\n      return done(null, { username });\n    }\n    return done(null, false);\n  }));\n\nLa función de verificación llama a `done(error, usuario)`: pasa `null, datosDelUsuario` en caso de éxito, o `null, false` si las credenciales son inválidas (reservando el primer argumento para errores inesperados, como un fallo de conexión a la base de datos).\n\nPara usar la estrategia en una ruta, invocas `passport.authenticate('local', opciones)` como middleware:\n\n  app.post('/login', passport.authenticate('local', { session: false }), (req, res) => {\n    res.json({ ok: true, user: req.user });\n  });\n\nCuando la autenticación tiene éxito, Passport completa `req.user` con el objeto devuelto por `done()`, y la solicitud continúa al siguiente manejador. Cuando falla, Passport responde automáticamente con `401 Unauthorized`.\n\nEn aplicaciones que usan sesiones (en lugar de JWT), Passport también define `serializeUser` (para decidir qué guardar en la sesión después del login — normalmente solo el ID del usuario) y `deserializeUser` (para reconstruir el usuario completo a partir de ese ID en cada solicitud posterior). La opción `{ session: false }`, usada aquí, desactiva esa integración, ya que este ejercicio se centra solo en la estrategia local en sí.",
    "de": "Passport.js ist die am häufigsten verwendete Authentifizierungs-Middleware im Express-Ökosystem. Statt die Login-Logik für jede Authentifizierungsmethode (Benutzername/Passwort, Google, GitHub, JWT...) von Grund auf neu zu implementieren, organisiert Passport dies in **Strategien** (`Strategy`) — austauschbare Module, die jeweils einen bestimmten Authentifizierungsmechanismus implementieren.\n\nDie `LocalStrategy` (aus dem Paket `passport-local`) implementiert den einfachsten Fall: Authentifizierung mit Benutzername und Passwort, lokal von deiner eigenen Anwendung validiert (statt von einem externen Anbieter wie Google). Du konfigurierst sie, indem du eine Verify-Funktion bereitstellst:\n\n  const LocalStrategy = require('passport-local').Strategy;\n\n  passport.use(new LocalStrategy((username, password, done) => {\n    if (username === 'admin' && password === '1234') {\n      return done(null, { username });\n    }\n    return done(null, false);\n  }));\n\nDie Verify-Funktion ruft `done(fehler, benutzer)` auf: übergib bei Erfolg `null, benutzerdaten`, oder `null, false`, wenn die Anmeldedaten ungültig sind (das erste Argument bleibt für unerwartete Fehler reserviert, wie einen fehlgeschlagenen Datenbankzugriff).\n\nUm die Strategie auf einer Route zu verwenden, rufst du `passport.authenticate('local', optionen)` als Middleware auf:\n\n  app.post('/login', passport.authenticate('local', { session: false }), (req, res) => {\n    res.json({ ok: true, user: req.user });\n  });\n\nWenn die Authentifizierung erfolgreich ist, befüllt Passport `req.user` mit dem von `done()` zurückgegebenen Objekt, und die Anfrage geht weiter zum nächsten Handler. Bei einem Fehlschlag antwortet Passport automatisch mit `401 Unauthorized`.\n\nIn Anwendungen, die Sitzungen (statt JWT) verwenden, definiert Passport zusätzlich `serializeUser` (um zu entscheiden, was nach dem Login in der Sitzung gespeichert wird — meist nur die Benutzer-ID) und `deserializeUser` (um den vollständigen Benutzer aus dieser ID bei jeder weiteren Anfrage zu rekonstruieren). Die hier verwendete Option `{ session: false }` deaktiviert diese Integration, da sich diese Übung ausschließlich auf die lokale Strategie konzentriert.",
    "it": "Passport.js è il middleware di autenticazione più usato nell'ecosistema Express. Invece di implementare da zero la logica di login per ogni metodo di autenticazione (username/password, Google, GitHub, JWT...), Passport organizza questo in **strategie** (`Strategy`) — moduli collegabili, ciascuno che implementa un meccanismo di autenticazione specifico.\n\nLa `LocalStrategy` (dal pacchetto `passport-local`) implementa il caso più semplice: autenticazione con username e password, validati localmente dalla tua stessa applicazione (invece di un provider esterno come Google). La configuri fornendo una funzione di verifica:\n\n  const LocalStrategy = require('passport-local').Strategy;\n\n  passport.use(new LocalStrategy((username, password, done) => {\n    if (username === 'admin' && password === '1234') {\n      return done(null, { username });\n    }\n    return done(null, false);\n  }));\n\nLa funzione di verifica chiama `done(errore, utente)`: passa `null, datiUtente` in caso di successo, o `null, false` se le credenziali sono invalide (riservando il primo argomento per errori imprevisti, come un fallimento di connessione al database).\n\nPer usare la strategia su una rotta, invochi `passport.authenticate('local', opzioni)` come middleware:\n\n  app.post('/login', passport.authenticate('local', { session: false }), (req, res) => {\n    res.json({ ok: true, user: req.user });\n  });\n\nQuando l'autenticazione ha successo, Passport popola `req.user` con l'oggetto restituito da `done()`, e la richiesta procede verso il prossimo handler. In caso di fallimento, Passport risponde automaticamente con `401 Unauthorized`.\n\nNelle applicazioni che usano sessioni (invece di JWT), Passport definisce anche `serializeUser` (per decidere cosa salvare nella sessione dopo il login — di solito solo l'ID dell'utente) e `deserializeUser` (per ricostruire l'utente completo a partire da quell'ID in ogni richiesta successiva). L'opzione `{ session: false }`, usata qui, disattiva quell'integrazione, poiché questo esercizio si concentra solo sulla strategia locale in sé.",
    "fr": "Passport.js est le middleware d'authentification le plus utilisé dans l'écosystème Express. Plutôt que d'implémenter la logique de connexion à partir de zéro pour chaque méthode d'authentification (nom d'utilisateur/mot de passe, Google, GitHub, JWT...), Passport organise cela en **stratégies** (`Strategy`) — des modules enfichables, chacun implémentant un mécanisme d'authentification spécifique.\n\nLa `LocalStrategy` (du paquet `passport-local`) implémente le cas le plus simple : authentification par nom d'utilisateur et mot de passe, validée localement par ta propre application (au lieu d'un fournisseur externe comme Google). Tu la configures en fournissant une fonction de vérification :\n\n  const LocalStrategy = require('passport-local').Strategy;\n\n  passport.use(new LocalStrategy((username, password, done) => {\n    if (username === 'admin' && password === '1234') {\n      return done(null, { username });\n    }\n    return done(null, false);\n  }));\n\nLa fonction de vérification appelle `done(erreur, utilisateur)` : passe `null, donneesUtilisateur` en cas de succès, ou `null, false` si les identifiants sont invalides (réservant le premier argument aux erreurs inattendues, comme un échec de connexion à la base de données).\n\nPour utiliser la stratégie sur une route, tu invoques `passport.authenticate('local', options)` comme middleware :\n\n  app.post('/login', passport.authenticate('local', { session: false }), (req, res) => {\n    res.json({ ok: true, user: req.user });\n  });\n\nLorsque l'authentification réussit, Passport remplit `req.user` avec l'objet renvoyé par `done()`, et la requête continue vers le handler suivant. En cas d'échec, Passport répond automatiquement avec `401 Unauthorized`.\n\nDans les applications qui utilisent des sessions (au lieu de JWT), Passport définit aussi `serializeUser` (pour décider quoi sauvegarder dans la session après la connexion — généralement juste l'ID de l'utilisateur) et `deserializeUser` (pour reconstruire l'utilisateur complet à partir de cet ID à chaque requête suivante). L'option `{ session: false }`, utilisée ici, désactive cette intégration, puisque cet exercice se concentre uniquement sur la stratégie locale elle-même."
  },
  "instructions": {
    "en": "Configure Passport.js with the `LocalStrategy` that validates username and password against a hardcoded users list. Wire up `passport.initialize()`, `passport.session()`, `serializeUser`, and `deserializeUser`. Implement `POST /login` and `GET /profile` routes.",
    "pt": "Configure o Passport.js com a `LocalStrategy` que valida usuário e senha contra uma lista de usuários hardcoded. Conecte `passport.initialize()`, `passport.session()`, `serializeUser` e `deserializeUser`. Implemente as rotas `POST /login` e `GET /profile`.",
    "es": "Configura Passport.js con la `LocalStrategy` que valida usuario y contraseña contra una lista de usuarios hardcodeada. Conecta `passport.initialize()`, `passport.session()`, `serializeUser` y `deserializeUser`. Implementa las rutas `POST /login` y `GET /profile`.",
    "de": "Konfiguriere Passport.js mit der `LocalStrategy`, die Benutzername und Passwort gegen eine hartcodierte Benutzerliste prüft. Verbinde `passport.initialize()`, `passport.session()`, `serializeUser` und `deserializeUser`. Implementiere die Routen `POST /login` und `GET /profile`.",
    "it": "Configura Passport.js con la `LocalStrategy` che valida username e password contro una lista di utenti hardcoded. Collega `passport.initialize()`, `passport.session()`, `serializeUser` e `deserializeUser`. Implementa le rotte `POST /login` e `GET /profile`.",
    "fr": "Configure Passport.js avec la `LocalStrategy` qui valide nom d'utilisateur et mot de passe contre une liste d'utilisateurs codée en dur. Connecte `passport.initialize()`, `passport.session()`, `serializeUser` et `deserializeUser`. Implémente les routes `POST /login` et `GET /profile`."
  },
  "starter": "const express = require('express');\nconst passport = require('passport');\nconst LocalStrategy = require('passport-local').Strategy;\n\nfunction createApp() {\n  passport.use(new LocalStrategy((username, password, done) => {\n    if (username === 'admin' && password === '1234') {\n      return __fill_me__;\n    }\n    return __fill_me__;\n  }));\n\n  const app = express();\n  app.use(express.json());\n  app.use(passport.initialize());\n\n  app.post('/login', passport.authenticate('local', { session: false }), (req, res) => {\n    res.json({ ok: true, user: req.user });\n  });\n\n  return app;\n}\n\nmodule.exports = { createApp };",
  "solution": "const express = require('express');\nconst passport = require('passport');\nconst LocalStrategy = require('passport-local').Strategy;\n\nfunction createApp() {\n  passport.use(new LocalStrategy((username, password, done) => {\n    if (username === 'admin' && password === '1234') {\n      return done(null, { username });\n    }\n    return done(null, false);\n  }));\n\n  const app = express();\n  app.use(express.json());\n  app.use(passport.initialize());\n\n  app.post('/login', passport.authenticate('local', { session: false }), (req, res) => {\n    res.json({ ok: true, user: req.user });\n  });\n\n  return app;\n}\n\nmodule.exports = { createApp };",
  "tests": [
    "const app = createApp(); const server = app.listen(3080); const res = await fetch('http://localhost:3080/login', { method: 'POST', headers: { 'Content-Type': 'application/json' }, body: JSON.stringify({ username: 'admin', password: '1234' }) }); const json = await res.json(); await new Promise((r) => server.close(r)); expect(res.status).toBe(200); expect(json.user.username).toBe('admin');",
    "const app2 = createApp(); const server2 = app2.listen(3081); const res2 = await fetch('http://localhost:3081/login', { method: 'POST', headers: { 'Content-Type': 'application/json' }, body: JSON.stringify({ username: 'admin', password: 'wrong' }) }); await new Promise((r) => server2.close(r)); expect(res2.status).toBe(401);"
  ]
}
